jupyter_server_mathjax/__init__.py
jupyter_server_mathjax/__version__.py
jupyter_server_mathjax/app.py
jupyter_server_mathjax/static/LICENSE
jupyter_server_mathjax/static/MathJax.js
jupyter_server_mathjax/static/config/Safe.js
jupyter_server_mathjax/static/config/TeX-AMS-MML_HTMLorMML-full.js
jupyter_server_mathjax/static/extensions/AssistiveMML.js
jupyter_server_mathjax/static/extensions/CHTML-preview.js
jupyter_server_mathjax/static/extensions/FontWarnings.js
jupyter_server_mathjax/static/extensions/HelpDialog.js
jupyter_server_mathjax/static/extensions/MatchWebFonts.js
jupyter_server_mathjax/static/extensions/MathEvents.js
jupyter_server_mathjax/static/extensions/MathMenu.js
jupyter_server_mathjax/static/extensions/MathZoom.js
jupyter_server_mathjax/static/extensions/Safe.js
jupyter_server_mathjax/static/extensions/asciimath2jax.js
jupyter_server_mathjax/static/extensions/fast-preview.js
jupyter_server_mathjax/static/extensions/jsMath2jax.js
jupyter_server_mathjax/static/extensions/mml2jax.js
jupyter_server_mathjax/static/extensions/tex2jax.js
jupyter_server_mathjax/static/extensions/toMathML.js
jupyter_server_mathjax/static/extensions/HTML-CSS/handle-floats.js
jupyter_server_mathjax/static/extensions/MathML/content-mathml.js
jupyter_server_mathjax/static/extensions/MathML/mml3.js
jupyter_server_mathjax/static/extensions/TeX/AMScd.js
jupyter_server_mathjax/static/extensions/TeX/AMSmath.js
jupyter_server_mathjax/static/extensions/TeX/AMSsymbols.js
jupyter_server_mathjax/static/extensions/TeX/HTML.js
jupyter_server_mathjax/static/extensions/TeX/action.js
jupyter_server_mathjax/static/extensions/TeX/autobold.js
jupyter_server_mathjax/static/extensions/TeX/autoload-all.js
jupyter_server_mathjax/static/extensions/TeX/bbox.js
jupyter_server_mathjax/static/extensions/TeX/begingroup.js
jupyter_server_mathjax/static/extensions/TeX/boldsymbol.js
jupyter_server_mathjax/static/extensions/TeX/cancel.js
jupyter_server_mathjax/static/extensions/TeX/color.js
jupyter_server_mathjax-0.2.6.dist-info/LICENSE
jupyter_server_mathjax-0.2.6.dist-info/METADATA
jupyter_server_mathjax-0.2.6.dist-info/WHEEL
jupyter_server_mathjax-0.2.6.dist-info/top_level.txt
jupyter_server_mathjax-0.2.6.dist-info/RECORD
