Metadata-Version: 2.1
Name: jupyter-server-mathjax
Version: 0.2.6
Summary: MathJax resources as a Jupyter Server Extension.
Home-page: http://jupyter.org
Author: Jupyter Development Team
Author-email: jupyter@googlegroups.com
License: BSD 3-Clause License
Keywords: ipython,jupyter,jupyter-server
Platform: Linux
Platform: Mac OS X
Platform: Windows
Classifier: Framework :: Jupyter
Classifier: Intended Audience :: Developers
Classifier: Intended Audience :: System Administrators
Classifier: Intended Audience :: Science/Research
Classifier: License :: OSI Approved :: BSD License
Classifier: Programming Language :: Python
Classifier: Programming Language :: Python :: 3
Classifier: Programming Language :: Python :: 3.7
Classifier: Programming Language :: Python :: 3.8
Classifier: Programming Language :: Python :: 3.9
Classifier: Programming Language :: Python :: 3.10
Requires-Python: >=3.7
Provides-Extra: test
License-File: LICENSE
